<?xml version="1.0" encoding="utf-8"?>
<list>
  <song id="1">
    <title>heavenly blue</title>
    <artist>Kalafina</artist>
    <album>ALDNOAH.ZERO OP Single - heave</album>
    <year>2014</year>
  </song>
  <song id="2">
    <title>Daisy</title>
    <artist>STEREO DIVE FOUNDATION</artist>
    <album>Daisy</album>
    <year>2013</year>
  </song>
  <song id="3">
    <title>A/Z</title>
    <artist>SawanoHiroyuki[nZk]:mizuki</artist>
    <album>ALDNOAH.ZERO ED &amp; Insert Song</album>
    <year>2014</year>
  </song>
</list>